damo/__init__.py
damo/_damo_ascii_color.py
damo/_damo_deprecated.py
damo/_damo_deprecation_notice.py
damo/_damo_dist.py
damo/_damo_fmt_str.py
damo/_damo_fs.py
damo/_damo_print.py
damo/_damo_records.py
damo/_damo_subcmds.py
damo/_damo_subproc.py
damo/_damo_sysinfo.py
damo/_damo_yaml.py
damo/_damon.py
damo/_damon_args.py
damo/_damon_dbgfs.py
damo/_damon_features.py
damo/_damon_sysfs.py
damo/damo.py
damo/damo_adjust.py
damo/damo_args.py
damo/damo_args_accesses_filter.py
damo/damo_args_accesses_format.py
damo/damo_args_damon.py
damo/damo_convert_record_format.py
damo/damo_diagnose.py
damo/damo_features.py
damo/damo_help.py
damo/damo_help_access_filter_options.py
damo/damo_help_access_format_options.py
damo/damo_help_damon_param_options.py
damo/damo_lru_sort.py
damo/damo_module.py
damo/damo_module_general.py
damo/damo_module_stat.py
damo/damo_monitor.py
damo/damo_nr_regions.py
damo/damo_pa_layout.py
damo/damo_reclaim.py
damo/damo_record.py
damo/damo_record_info.py
damo/damo_replay.py
damo/damo_report.py
damo/damo_report_access.py
damo/damo_report_damon.py
damo/damo_report_footprint.py
damo/damo_report_heatmap.py
damo/damo_report_holistic.py
damo/damo_report_profile.py
damo/damo_report_sysinfo.py
damo/damo_report_times.py
damo/damo_schemes.py
damo/damo_start.py
damo/damo_stop.py
damo/damo_tune.py
damo/damo_validate.py
damo/damo_version.py
damo/damo_wss.py
damo-3.1.1.dist-info/METADATA
damo-3.1.1.dist-info/WHEEL
damo-3.1.1.dist-info/entry_points.txt
damo-3.1.1.dist-info/top_level.txt
damo-3.1.1.dist-info/RECORD
