Metadata-Version: 2.4
Name: damo
Version: 3.1.1
Summary: DAMON user-space tool
Home-page: https://github.com/damonitor/damo
Author: SeongJae Park
Author-email: sj@kernel.org
Project-URL: Bug Tracker, https://github.com/damonitor/damo/issues
Project-URL: DAMON, https://damonitor.github.io
Classifier: Programming Language :: Python :: 3
Classifier: License :: OSI Approved :: GNU General Public License v2 (GPLv2)
Classifier: Operating System :: POSIX :: Linux
Requires-Python: >=3.6
Dynamic: author
Dynamic: author-email
Dynamic: classifier
Dynamic: description
Dynamic: description-content-type
Dynamic: home-page
Dynamic: project-url
Dynamic: requires-python
Dynamic: summary
